{"accuracy": 0.8, "correct_count": 40, "total_count": 50}
{"id": 3, "model_name": "claude-instant-1.2", "test_category": "executable_parallel_function", "valid": false, "error": ["Could not find a matching function among index [0, 1, 2, 3] of model output for index 0 of possible answers.", {"Model Result Index 0": {"sub_error": ["Wrong execution result for 'calculate_density(mass=0.5,volume=0.1)'. Expected: 5000.0, but got: 5.0."], "sub_error_type": "executable_checker:wrong_result", "model_executed_output": 5.0}}, {"Model Result Index 1": {"sub_error": ["Wrong execution result for 'calculate_density(mass=0.2,volume=0.05)'. Expected: 5000.0, but got: 4.0."], "sub_error_type": "executable_checker:wrong_result", "model_executed_output": 4.0}}, {"Model Result Index 2": {"sub_error": ["Wrong execution result for 'calculate_density(mass=0.3,volume=0.075)'. Expected: 5000.0, but got: 4.0."], "sub_error_type": "executable_checker:wrong_result", "model_executed_output": 4.0}}, {"Model Result Index 3": {"sub_error": ["Wrong execution result for 'calculate_density(mass=0.4,volume=0.08)'. Expected: 5000.0, but got: 5.0."], "sub_error_type": "executable_checker:wrong_result", "model_executed_output": 5.0}}], "error_type": "executable_checker:cannot_find_match", "prompt": {"id": "executable_parallel_function_2", "question": "I'm conducting an experiment with four objects of different materials and need to calculate their densities. The metal cube weighs 500 grams and takes up 100 cc, the plastic sphere is 200 grams and 50 cc, the wooden block is 300 grams and has a volume of 75 cc, and the glass cylinder is 400 grams with an 80 cc volume. Could you determine the density for each one?", "function": {"name": "calculate_density", "description": "Calculates the density of an object.", "parameters": {"type": "dict", "properties": {"mass": {"type": "float", "description": "The mass of the object, in kilograms."}, "volume": {"type": "float", "description": "The volume of the object, in cubic meters."}}, "required": ["mass", "volume"]}}, "execution_result_type": ["exact_match", "exact_match", "exact_match", "exact_match"], "ground_truth": ["calculate_density(mass=0.5, volume=0.0001)", "calculate_density(mass=0.2, volume=0.00005)", "calculate_density(mass=0.3, volume=0.000075)", "calculate_density(mass=0.4, volume=0.00008)"], "execution_result": [5000.0, 4000.0, 4000.0, 5000.0]}, "model_result_raw": "[calculate_density(mass=0.5, volume=0.1), calculate_density(mass=0.2, volume=0.05), calculate_density(mass=0.3, volume=0.075), calculate_density(mass=0.4, volume=0.08)]", "model_result_decoded": ["calculate_density(mass=0.5,volume=0.1)", "calculate_density(mass=0.2,volume=0.05)", "calculate_density(mass=0.3,volume=0.075)", "calculate_density(mass=0.4,volume=0.08)"]}
{"id": 11, "model_name": "claude-instant-1.2", "test_category": "executable_parallel_function", "valid": false, "error": ["Could not find a matching function among index [1, 2] of model output for index 1 of possible answers.", {"Model Result Index 1": {"sub_error": ["Wrong execution result for 'calculate_triangle_area(base=7.62,height=9.144)'. Expected: 375.0, but got: 34.83864."], "sub_error_type": "executable_checker:wrong_result", "model_executed_output": 34.83864}}, {"Model Result Index 2": {"sub_error": ["Wrong execution result for 'calculate_triangle_area(base=13.779527559055119,height=15.748031496062993)'. Expected: 375.0, but got: 108.500217000434."], "sub_error_type": "executable_checker:wrong_result", "model_executed_output": 108.500217000434}}], "error_type": "executable_checker:cannot_find_match", "prompt": {"id": "executable_parallel_function_10", "question": "I need to calculate the area of three different triangles for a construction project I'm working on: one with a base of 15 meters and a height of 20 meters, another with a base of 25 feet and a height of 30 feet, and a third with dimensions of 35 inches by 40 inches for the base and height, respectively. Can you give me the areas for each triangle?", "function": {"name": "calculate_triangle_area", "description": "Calculates the area of a triangle given its base and height.", "parameters": {"type": "dict", "properties": {"base": {"type": "integer", "description": "The base of the triangle, in meters."}, "height": {"type": "integer", "description": "The height of the triangle, in meters."}}, "required": ["base", "height"]}}, "execution_result_type": ["exact_match", "exact_match", "exact_match"], "ground_truth": ["calculate_triangle_area(base=15, height=20)", "calculate_triangle_area(base=25, height=30)", "calculate_triangle_area(base=35, height=40)"], "execution_result": [150.0, 375.0, 700.0]}, "model_result_raw": "[calculate_triangle_area(base=15, height=20), calculate_triangle_area(base=25*0.3048, height=30*0.3048), calculate_triangle_area(base=35/2.54, height=40/2.54)]", "model_result_decoded": ["calculate_triangle_area(base=15,height=20)", "calculate_triangle_area(base=7.62,height=9.144)", "calculate_triangle_area(base=13.779527559055119,height=15.748031496062993)"]}
{"id": 13, "model_name": "claude-instant-1.2", "test_category": "executable_parallel_function", "valid": false, "error": ["Could not find a matching function among index [0, 1, 2, 3] of model output for index 0 of possible answers.", {"Model Result Index 0": {"sub_error": ["Error in execution: \"estimate_derivative(function='f(x) = 3x^2 + 2x - 1',x=4)\". Error: invalid decimal literal (<string>, line 1)"], "sub_error_type": "executable_checker:execution_error", "model_executed_output": null}}, {"Model Result Index 1": {"sub_error": ["Error in execution: \"estimate_derivative(function='g(x) = 5x^3 - 3x^2 + 2x + 1',x=-2)\". Error: invalid decimal literal (<string>, line 1)"], "sub_error_type": "executable_checker:execution_error", "model_executed_output": null}}, {"Model Result Index 2": {"sub_error": ["Error in execution: \"estimate_derivative(function='h(x) = 2x^4 - 3x^3 + 2x^2 - x + 1',x=0)\". Error: invalid decimal literal (<string>, line 1)"], "sub_error_type": "executable_checker:execution_error", "model_executed_output": null}}, {"Model Result Index 3": {"sub_error": ["Error in execution: \"estimate_derivative(function='i(x) = x^5 - 2x^4 + 3x^3 - 2x^2 + x - 1',x=1)\". Error: invalid decimal literal (<string>, line 1)"], "sub_error_type": "executable_checker:execution_error", "model_executed_output": null}}], "error_type": "executable_checker:cannot_find_match", "prompt": {"id": "executable_parallel_function_12", "question": "I'm working on some calculus problems and need help estimating derivatives. Could you find the derivative of f(x) = 3x^2 + 2x - 1 at x = 4, calculate the derivative of g(x) = 5x^3 - 3x^2 + 2x + 1 at x = -2, determine the derivative of h(x) = 2x^4 - 3x^3 + 2x^2 - x + 1 at x = 0, and get the derivative of i(x) = x^5 - 2x^4 + 3x^3 - 2x^2 + x - 1 at x = 1?", "function": {"name": "estimate_derivative", "description": "Estimate the derivative of a function at a given point.", "parameters": {"type": "dict", "properties": {"function": {"type": "string", "description": "The function to calculate the derivative of."}, "x": {"type": "integer", "description": "The point to calculate the derivative at."}}, "required": ["function", "x"]}}, "execution_result_type": ["exact_match", "exact_match", "exact_match", "exact_match"], "ground_truth": ["estimate_derivative(function='lambda x: 3*x**2 + 2*x - 1', x=4)", "estimate_derivative(function='lambda x: 5*x**3 - 3*x**2 + 2*x + 1', x=-2)", "estimate_derivative(function='lambda x: 2*x**4 - 3*x**3 + 2*x**2 - x + 1', x=0)", "estimate_derivative(function='lambda x: x**5 - 2*x**4 + 3*x**3 - 2*x**2 + x - 1', x=1)"], "execution_result": [26.000037678386434, 74.00004164992424, -1.000000082740371, 3.000000248221113]}, "model_result_raw": "[estimate_derivative(function=\"f(x) = 3x^2 + 2x - 1\", x=4),\n        estimate_derivative(function=\"g(x) = 5x^3 - 3x^2 + 2x + 1\", x=-2),\n        estimate_derivative(function=\"h(x) = 2x^4 - 3x^3 + 2x^2 - x + 1\", x=0),\n        estimate_derivative(function=\"i(x) = x^5 - 2x^4 + 3x^3 - 2x^2 + x - 1\", x=1)]", "model_result_decoded": ["estimate_derivative(function='f(x) = 3x^2 + 2x - 1',x=4)", "estimate_derivative(function='g(x) = 5x^3 - 3x^2 + 2x + 1',x=-2)", "estimate_derivative(function='h(x) = 2x^4 - 3x^3 + 2x^2 - x + 1',x=0)", "estimate_derivative(function='i(x) = x^5 - 2x^4 + 3x^3 - 2x^2 + x - 1',x=1)"]}
{"id": 16, "model_name": "claude-instant-1.2", "test_category": "executable_parallel_function", "valid": false, "error": ["Could not find a matching function among index [2, 3] of model output for index 2 of possible answers.", {"Model Result Index 2": {"sub_error": ["Wrong execution result for \"get_active_covid_case_by_country(country='United States')\". Expected: {'get': 'statistics', 'parameters': {'country': 'United States'}, 'errors': [], 'results': 0, 'response': []}, but got: {'get': 'statistics', 'parameters': {'country': 'United States'}, 'errors': [], 'results': 0, 'response': []}. Type needs to be float or int for real time match criteria."], "sub_error_type": "executable_checker:wrong_result_real_time", "model_executed_output": {"get": "statistics", "parameters": {"country": "United States"}, "errors": [], "results": 0, "response": []}}}, {"Model Result Index 3": {"sub_error": ["Wrong execution result for \"get_active_covid_case_by_country(country='China')\". Expected: {'get': 'statistics', 'parameters': {'country': 'United States'}, 'errors': [], 'results': 0, 'response': []}, but got: 118977. Type needs to be float or int for real time match criteria."], "sub_error_type": "executable_checker:wrong_result_real_time", "model_executed_output": 118977}}], "error_type": "executable_checker:cannot_find_match", "prompt": {"id": "executable_parallel_function_15", "question": "With the pandemic still lingering, I'm trying to stay updated on the COVID-19 situation around the globe. I'm particularly interested in the current active case numbers for a few countries. Could you provide me with the latest figures for active COVID-19 cases in France, Italy, the United States, and China?", "function": {"name": "get_active_covid_case_by_country", "description": "Finds the most up to date active cases of a country result from COVID.", "parameters": {"type": "dict", "properties": {"country": {"type": "string", "description": "The country to find the active cases of, in the format of the country's full name."}}, "required": ["country"]}}, "execution_result_type": ["real_time_match", "real_time_match", "real_time_match", "real_time_match"], "ground_truth": ["get_active_covid_case_by_country(country='France')", "get_active_covid_case_by_country(country='Italy')", "get_active_covid_case_by_country(country='United States')", "get_active_covid_case_by_country(country='China')"], "execution_result": [0, 165544, {"get": "statistics", "parameters": {"country": "United States"}, "errors": [], "results": 0, "response": []}, 118977]}, "model_result_raw": "[get_active_covid_case_by_country(country='France'),get_active_covid_case_by_country(country='Italy'),get_active_covid_case_by_country(country='United States'),get_active_covid_case_by_country(country='China')]", "model_result_decoded": ["get_active_covid_case_by_country(country='France')", "get_active_covid_case_by_country(country='Italy')", "get_active_covid_case_by_country(country='United States')", "get_active_covid_case_by_country(country='China')"]}
{"id": 39, "model_name": "claude-instant-1.2", "test_category": "executable_parallel_function", "valid": false, "error": ["Could not find a matching function among index [0, 1, 2] of model output for index 1 of possible answers.", {"Model Result Index 0": {"sub_error": ["Wrong execution result for \"retrieve_holiday_by_year(year='2018',country='DE')\". Expected: [{'date': '2020-01-01', 'localName': 'Neujahr', 'name': \"New Year's Day\", 'countryCode': 'DE', 'fixed': False, 'global': True, 'counties': None, 'launchYear': None, 'types': ['Public']}, {'date': '2020-01-06', 'localName': 'Heilige Drei K\u00f6nige', 'name': 'Epiphany', 'countryCode': 'DE', 'fixed': False, 'global': False, 'counties': ['DE-BW', 'DE-BY', 'DE-ST'], 'launchYear': None, 'types': ['Public']}, {'date': '2020-03-08', 'localName': 'Internationaler Frauentag', 'name': \"International Women's Day\", 'countryCode': 'DE', 'fixed': False, 'global': False, 'counties': ['DE-BE'], 'launchYear': None, 'types': ['Public']}, {'date': '2020-04-10', 'localName': 'Karfreitag', 'name': 'Good Friday', 'countryCode': 'DE', 'fixed': False, 'global': True, 'counties': None, 'launchYear': None, 'types': ['Public']}, {'date': '2020-04-12', 'localName': 'Ostersonntag', 'name': 'Easter Sunday', 'countryCode': 'DE', 'fixed': False, 'global': False, 'counties': ['DE-BB'], 'launchYear': None, 'types': ['Public']}, {'date': '2020-04-13', 'localName': 'Ostermontag', 'name': 'Easter Monday', 'countryCode': 'DE', 'fixed': False, 'global': True, 'counties': None, 'launchYear': None, 'types': ['Public']}, {'date': '2020-05-01', 'localName': 'Tag der Arbeit', 'name': 'Labour Day', 'countryCode': 'DE', 'fixed': False, 'global': True, 'counties': None, 'launchYear': None, 'types': ['Public']}, {'date': '2020-05-08', 'localName': 'Tag der Befreiung', 'name': 'Liberation Day', 'countryCode': 'DE', 'fixed': False, 'global': False, 'counties': ['DE-BE'], 'launchYear': None, 'types': ['Public']}, {'date': '2020-05-21', 'localName': 'Christi Himmelfahrt', 'name': 'Ascension Day', 'countryCode': 'DE', 'fixed': False, 'global': True, 'counties': None, 'launchYear': None, 'types': ['Public']}, {'date': '2020-05-31', 'localName': 'Pfingstsonntag', 'name': 'Pentecost', 'countryCode': 'DE', 'fixed': False, 'global': False, 'counties': ['DE-BB', 'DE-HE'], 'launchYear': None, 'types': ['Public']}, {'date': '2020-06-01', 'localName': 'Pfingstmontag', 'name': 'Whit Monday', 'countryCode': 'DE', 'fixed': False, 'global': True, 'counties': None, 'launchYear': None, 'types': ['Public']}, {'date': '2020-06-11', 'localName': 'Fronleichnam', 'name': 'Corpus Christi', 'countryCode': 'DE', 'fixed': False, 'global': False, 'counties': ['DE-BW', 'DE-BY', 'DE-HE', 'DE-NW', 'DE-RP', 'DE-SL'], 'launchYear': None, 'types': ['Public']}, {'date': '2020-08-15', 'localName': 'Mari\u00e4 Himmelfahrt', 'name': 'Assumption Day', 'countryCode': 'DE', 'fixed': False, 'global': False, 'counties': ['DE-SL'], 'launchYear': None, 'types': ['Public']}, {'date': '2020-09-20', 'localName': 'Weltkindertag', 'name': \"World Children's Day\", 'countryCode': 'DE', 'fixed': False, 'global': False, 'counties': ['DE-TH'], 'launchYear': None, 'types': ['Public']}, {'date': '2020-10-03', 'localName': 'Tag der Deutschen Einheit', 'name': 'German Unity Day', 'countryCode': 'DE', 'fixed': False, 'global': True, 'counties': None, 'launchYear': None, 'types': ['Public']}, {'date': '2020-10-31', 'localName': 'Reformationstag', 'name': 'Reformation Day', 'countryCode': 'DE', 'fixed': False, 'global': False, 'counties': ['DE-BB', 'DE-MV', 'DE-SN', 'DE-ST', 'DE-TH', 'DE-HB', 'DE-HH', 'DE-NI', 'DE-SH'], 'launchYear': None, 'types': ['Public']}, {'date': '2020-11-01', 'localName': 'Allerheiligen', 'name': \"All Saints' Day\", 'countryCode': 'DE', 'fixed': False, 'global': False, 'counties': ['DE-BW', 'DE-BY', 'DE-NW', 'DE-RP', 'DE-SL'], 'launchYear': None, 'types': ['Public']}, {'date': '2020-11-18', 'localName': 'Bu\u00df- und Bettag', 'name': 'Repentance and Prayer Day', 'countryCode': 'DE', 'fixed': False, 'global': False, 'counties': ['DE-SN'], 'launchYear': None, 'types': ['Public']}, {'date': '2020-12-25', 'localName': 'Erster Weihnachtstag', 'name': 'Christmas Day', 'countryCode': 'DE', 'fixed': False, 'global': True, 'counties': None, 'launchYear': None, 'types': ['Public']}, {'date': '2020-12-26', 'localName': 'Zweiter Weihnachtstag', 'name': \"St. Stephen's Day\", 'countryCode': 'DE', 'fixed': False, 'global': True, 'counties': None, 'launchYear': None, 'types': ['Public']}], but got: [{'date': '2018-01-01', 'localName': 'Neujahr', 'name': \"New Year's Day\", 'countryCode': 'DE', 'fixed': False, 'global': True, 'counties': None, 'launchYear': None, 'types': ['Public']}, {'date': '2018-01-06', 'localName': 'Heilige Drei K\u00f6nige', 'name': 'Epiphany', 'countryCode': 'DE', 'fixed': False, 'global': False, 'counties': ['DE-BW', 'DE-BY', 'DE-ST'], 'launchYear': None, 'types': ['Public']}, {'date': '2018-03-30', 'localName': 'Karfreitag', 'name': 'Good Friday', 'countryCode': 'DE', 'fixed': False, 'global': True, 'counties': None, 'launchYear': None, 'types': ['Public']}, {'date': '2018-04-01', 'localName': 'Ostersonntag', 'name': 'Easter Sunday', 'countryCode': 'DE', 'fixed': False, 'global': False, 'counties': ['DE-BB'], 'launchYear': None, 'types': ['Public']}, {'date': '2018-04-02', 'localName': 'Ostermontag', 'name': 'Easter Monday', 'countryCode': 'DE', 'fixed': False, 'global': True, 'counties': None, 'launchYear': None, 'types': ['Public']}, {'date': '2018-05-01', 'localName': 'Tag der Arbeit', 'name': 'Labour Day', 'countryCode': 'DE', 'fixed': False, 'global': True, 'counties': None, 'launchYear': None, 'types': ['Public']}, {'date': '2018-05-10', 'localName': 'Christi Himmelfahrt', 'name': 'Ascension Day', 'countryCode': 'DE', 'fixed': False, 'global': True, 'counties': None, 'launchYear': None, 'types': ['Public']}, {'date': '2018-05-20', 'localName': 'Pfingstsonntag', 'name': 'Pentecost', 'countryCode': 'DE', 'fixed': False, 'global': False, 'counties': ['DE-BB', 'DE-HE'], 'launchYear': None, 'types': ['Public']}, {'date': '2018-05-21', 'localName': 'Pfingstmontag', 'name': 'Whit Monday', 'countryCode': 'DE', 'fixed': False, 'global': True, 'counties': None, 'launchYear': None, 'types': ['Public']}, {'date': '2018-05-31', 'localName': 'Fronleichnam', 'name': 'Corpus Christi', 'countryCode': 'DE', 'fixed': False, 'global': False, 'counties': ['DE-BW', 'DE-BY', 'DE-HE', 'DE-NW', 'DE-RP', 'DE-SL'], 'launchYear': None, 'types': ['Public']}, {'date': '2018-08-15', 'localName': 'Mari\u00e4 Himmelfahrt', 'name': 'Assumption Day', 'countryCode': 'DE', 'fixed': False, 'global': False, 'counties': ['DE-SL'], 'launchYear': None, 'types': ['Public']}, {'date': '2018-10-03', 'localName': 'Tag der Deutschen Einheit', 'name': 'German Unity Day', 'countryCode': 'DE', 'fixed': False, 'global': True, 'counties': None, 'launchYear': None, 'types': ['Public']}, {'date': '2018-10-31', 'localName': 'Reformationstag', 'name': 'Reformation Day', 'countryCode': 'DE', 'fixed': False, 'global': False, 'counties': ['DE-BB', 'DE-MV', 'DE-SN', 'DE-ST', 'DE-TH', 'DE-HB', 'DE-HH', 'DE-NI', 'DE-SH'], 'launchYear': None, 'types': ['Public']}, {'date': '2018-11-01', 'localName': 'Allerheiligen', 'name': \"All Saints' Day\", 'countryCode': 'DE', 'fixed': False, 'global': False, 'counties': ['DE-BW', 'DE-BY', 'DE-NW', 'DE-RP', 'DE-SL'], 'launchYear': None, 'types': ['Public']}, {'date': '2018-11-21', 'localName': 'Bu\u00df- und Bettag', 'name': 'Repentance and Prayer Day', 'countryCode': 'DE', 'fixed': False, 'global': False, 'counties': ['DE-SN'], 'launchYear': None, 'types': ['Public']}, {'date': '2018-12-25', 'localName': 'Erster Weihnachtstag', 'name': 'Christmas Day', 'countryCode': 'DE', 'fixed': False, 'global': True, 'counties': None, 'launchYear': None, 'types': ['Public']}, {'date': '2018-12-26', 'localName': 'Zweiter Weihnachtstag', 'name': \"St. Stephen's Day\", 'countryCode': 'DE', 'fixed': False, 'global': True, 'counties': None, 'launchYear': None, 'types': ['Public']}]."], "sub_error_type": "executable_checker:wrong_result", "model_executed_output": [{"date": "2018-01-01", "localName": "Neujahr", "name": "New Year's Day", "countryCode": "DE", "fixed": false, "global": true, "counties": null, "launchYear": null, "types": ["Public"]}, {"date": "2018-01-06", "localName": "Heilige Drei K\u00f6nige", "name": "Epiphany", "countryCode": "DE", "fixed": false, "global": false, "counties": ["DE-BW", "DE-BY", "DE-ST"], "launchYear": null, "types": ["Public"]}, {"date": "2018-03-30", "localName": "Karfreitag", "name": "Good Friday", "countryCode": "DE", "fixed": false, "global": true, "counties": null, "launchYear": null, "types": ["Public"]}, {"date": "2018-04-01", "localName": "Ostersonntag", "name": "Easter Sunday", "countryCode": "DE", "fixed": false, "global": false, "counties": ["DE-BB"], "launchYear": null, "types": ["Public"]}, {"date": "2018-04-02", "localName": "Ostermontag", "name": "Easter Monday", "countryCode": "DE", "fixed": false, "global": true, "counties": null, "launchYear": null, "types": ["Public"]}, {"date": "2018-05-01", "localName": "Tag der Arbeit", "name": "Labour Day", "countryCode": "DE", "fixed": false, "global": true, "counties": null, "launchYear": null, "types": ["Public"]}, {"date": "2018-05-10", "localName": "Christi Himmelfahrt", "name": "Ascension Day", "countryCode": "DE", "fixed": false, "global": true, "counties": null, "launchYear": null, "types": ["Public"]}, {"date": "2018-05-20", "localName": "Pfingstsonntag", "name": "Pentecost", "countryCode": "DE", "fixed": false, "global": false, "counties": ["DE-BB", "DE-HE"], "launchYear": null, "types": ["Public"]}, {"date": "2018-05-21", "localName": "Pfingstmontag", "name": "Whit Monday", "countryCode": "DE", "fixed": false, "global": true, "counties": null, "launchYear": null, "types": ["Public"]}, {"date": "2018-05-31", "localName": "Fronleichnam", "name": "Corpus Christi", "countryCode": "DE", "fixed": false, "global": false, "counties": ["DE-BW", "DE-BY", "DE-HE", "DE-NW", "DE-RP", "DE-SL"], "launchYear": null, "types": ["Public"]}, {"date": "2018-08-15", "localName": "Mari\u00e4 Himmelfahrt", "name": "Assumption Day", "countryCode": "DE", "fixed": false, "global": false, "counties": ["DE-SL"], "launchYear": null, "types": ["Public"]}, {"date": "2018-10-03", "localName": "Tag der Deutschen Einheit", "name": "German Unity Day", "countryCode": "DE", "fixed": false, "global": true, "counties": null, "launchYear": null, "types": ["Public"]}, {"date": "2018-10-31", "localName": "Reformationstag", "name": "Reformation Day", "countryCode": "DE", "fixed": false, "global": false, "counties": ["DE-BB", "DE-MV", "DE-SN", "DE-ST", "DE-TH", "DE-HB", "DE-HH", "DE-NI", "DE-SH"], "launchYear": null, "types": ["Public"]}, {"date": "2018-11-01", "localName": "Allerheiligen", "name": "All Saints' Day", "countryCode": "DE", "fixed": false, "global": false, "counties": ["DE-BW", "DE-BY", "DE-NW", "DE-RP", "DE-SL"], "launchYear": null, "types": ["Public"]}, {"date": "2018-11-21", "localName": "Bu\u00df- und Bettag", "name": "Repentance and Prayer Day", "countryCode": "DE", "fixed": false, "global": false, "counties": ["DE-SN"], "launchYear": null, "types": ["Public"]}, {"date": "2018-12-25", "localName": "Erster Weihnachtstag", "name": "Christmas Day", "countryCode": "DE", "fixed": false, "global": true, "counties": null, "launchYear": null, "types": ["Public"]}, {"date": "2018-12-26", "localName": "Zweiter Weihnachtstag", "name": "St. Stephen's Day", "countryCode": "DE", "fixed": false, "global": true, "counties": null, "launchYear": null, "types": ["Public"]}]}}, {"Model Result Index 1": {"sub_error": ["Wrong execution result for \"retrieve_holiday_by_year(year='2019',country='ES')\". Expected: [{'date': '2020-01-01', 'localName': 'Neujahr', 'name': \"New Year's Day\", 'countryCode': 'DE', 'fixed': False, 'global': True, 'counties': None, 'launchYear': None, 'types': ['Public']}, {'date': '2020-01-06', 'localName': 'Heilige Drei K\u00f6nige', 'name': 'Epiphany', 'countryCode': 'DE', 'fixed': False, 'global': False, 'counties': ['DE-BW', 'DE-BY', 'DE-ST'], 'launchYear': None, 'types': ['Public']}, {'date': '2020-03-08', 'localName': 'Internationaler Frauentag', 'name': \"International Women's Day\", 'countryCode': 'DE', 'fixed': False, 'global': False, 'counties': ['DE-BE'], 'launchYear': None, 'types': ['Public']}, {'date': '2020-04-10', 'localName': 'Karfreitag', 'name': 'Good Friday', 'countryCode': 'DE', 'fixed': False, 'global': True, 'counties': None, 'launchYear': None, 'types': ['Public']}, {'date': '2020-04-12', 'localName': 'Ostersonntag', 'name': 'Easter Sunday', 'countryCode': 'DE', 'fixed': False, 'global': False, 'counties': ['DE-BB'], 'launchYear': None, 'types': ['Public']}, {'date': '2020-04-13', 'localName': 'Ostermontag', 'name': 'Easter Monday', 'countryCode': 'DE', 'fixed': False, 'global': True, 'counties': None, 'launchYear': None, 'types': ['Public']}, {'date': '2020-05-01', 'localName': 'Tag der Arbeit', 'name': 'Labour Day', 'countryCode': 'DE', 'fixed': False, 'global': True, 'counties': None, 'launchYear': None, 'types': ['Public']}, {'date': '2020-05-08', 'localName': 'Tag der Befreiung', 'name': 'Liberation Day', 'countryCode': 'DE', 'fixed': False, 'global': False, 'counties': ['DE-BE'], 'launchYear': None, 'types': ['Public']}, {'date': '2020-05-21', 'localName': 'Christi Himmelfahrt', 'name': 'Ascension Day', 'countryCode': 'DE', 'fixed': False, 'global': True, 'counties': None, 'launchYear': None, 'types': ['Public']}, {'date': '2020-05-31', 'localName': 'Pfingstsonntag', 'name': 'Pentecost', 'countryCode': 'DE', 'fixed': False, 'global': False, 'counties': ['DE-BB', 'DE-HE'], 'launchYear': None, 'types': ['Public']}, {'date': '2020-06-01', 'localName': 'Pfingstmontag', 'name': 'Whit Monday', 'countryCode': 'DE', 'fixed': False, 'global': True, 'counties': None, 'launchYear': None, 'types': ['Public']}, {'date': '2020-06-11', 'localName': 'Fronleichnam', 'name': 'Corpus Christi', 'countryCode': 'DE', 'fixed': False, 'global': False, 'counties': ['DE-BW', 'DE-BY', 'DE-HE', 'DE-NW', 'DE-RP', 'DE-SL'], 'launchYear': None, 'types': ['Public']}, {'date': '2020-08-15', 'localName': 'Mari\u00e4 Himmelfahrt', 'name': 'Assumption Day', 'countryCode': 'DE', 'fixed': False, 'global': False, 'counties': ['DE-SL'], 'launchYear': None, 'types': ['Public']}, {'date': '2020-09-20', 'localName': 'Weltkindertag', 'name': \"World Children's Day\", 'countryCode': 'DE', 'fixed': False, 'global': False, 'counties': ['DE-TH'], 'launchYear': None, 'types': ['Public']}, {'date': '2020-10-03', 'localName': 'Tag der Deutschen Einheit', 'name': 'German Unity Day', 'countryCode': 'DE', 'fixed': False, 'global': True, 'counties': None, 'launchYear': None, 'types': ['Public']}, {'date': '2020-10-31', 'localName': 'Reformationstag', 'name': 'Reformation Day', 'countryCode': 'DE', 'fixed': False, 'global': False, 'counties': ['DE-BB', 'DE-MV', 'DE-SN', 'DE-ST', 'DE-TH', 'DE-HB', 'DE-HH', 'DE-NI', 'DE-SH'], 'launchYear': None, 'types': ['Public']}, {'date': '2020-11-01', 'localName': 'Allerheiligen', 'name': \"All Saints' Day\", 'countryCode': 'DE', 'fixed': False, 'global': False, 'counties': ['DE-BW', 'DE-BY', 'DE-NW', 'DE-RP', 'DE-SL'], 'launchYear': None, 'types': ['Public']}, {'date': '2020-11-18', 'localName': 'Bu\u00df- und Bettag', 'name': 'Repentance and Prayer Day', 'countryCode': 'DE', 'fixed': False, 'global': False, 'counties': ['DE-SN'], 'launchYear': None, 'types': ['Public']}, {'date': '2020-12-25', 'localName': 'Erster Weihnachtstag', 'name': 'Christmas Day', 'countryCode': 'DE', 'fixed': False, 'global': True, 'counties': None, 'launchYear': None, 'types': ['Public']}, {'date': '2020-12-26', 'localName': 'Zweiter Weihnachtstag', 'name': \"St. Stephen's Day\", 'countryCode': 'DE', 'fixed': False, 'global': True, 'counties': None, 'launchYear': None, 'types': ['Public']}], but got: [{'date': '2019-01-01', 'localName': 'A\u00f1o Nuevo', 'name': \"New Year's Day\", 'countryCode': 'ES', 'fixed': False, 'global': True, 'counties': None, 'launchYear': None, 'types': ['Public']}, {'date': '2019-01-06', 'localName': 'D\u00eda de Reyes / Epifan\u00eda del Se\u00f1or', 'name': 'Epiphany', 'countryCode': 'ES', 'fixed': False, 'global': True, 'counties': None, 'launchYear': None, 'types': ['Public']}, {'date': '2019-02-28', 'localName': 'D\u00eda de Andaluc\u00eda', 'name': 'Day of Andaluc\u00eda', 'countryCode': 'ES', 'fixed': False, 'global': False, 'counties': ['ES-AN'], 'launchYear': None, 'types': ['Public']}, {'date': '2019-03-01', 'localName': 'Dia de les Illes Balears', 'name': 'Day of the Balearic Islands', 'countryCode': 'ES', 'fixed': False, 'global': False, 'counties': ['ES-IB'], 'launchYear': None, 'types': ['Public']}, {'date': '2019-03-19', 'localName': 'San Jos\u00e9', 'name': \"St. Joseph's Day\", 'countryCode': 'ES', 'fixed': False, 'global': False, 'counties': ['ES-GA', 'ES-PV', 'ES-VC'], 'launchYear': None, 'types': ['Public']}, {'date': '2019-04-18', 'localName': 'Jueves Santo', 'name': 'Maundy Thursday', 'countryCode': 'ES', 'fixed': False, 'global': False, 'counties': ['ES-AN', 'ES-AR', 'ES-CL', 'ES-CM', 'ES-CN', 'ES-EX', 'ES-GA', 'ES-IB', 'ES-RI', 'ES-MD', 'ES-MC', 'ES-NC', 'ES-AS', 'ES-PV', 'ES-CB'], 'launchYear': None, 'types': ['Public']}, {'date': '2019-04-19', 'localName': 'Viernes Santo', 'name': 'Good Friday', 'countryCode': 'ES', 'fixed': False, 'global': True, 'counties': None, 'launchYear': None, 'types': ['Public']}, {'date': '2019-04-22', 'localName': 'Lunes de Pascua', 'name': 'Easter Monday', 'countryCode': 'ES', 'fixed': False, 'global': False, 'counties': ['ES-CT', 'ES-IB', 'ES-RI', 'ES-NC', 'ES-PV', 'ES-VC'], 'launchYear': None, 'types': ['Public']}, {'date': '2019-04-23', 'localName': 'D\u00eda de Castilla y Le\u00f3n', 'name': 'Castile and Le\u00f3n Day', 'countryCode': 'ES', 'fixed': False, 'global': False, 'counties': ['ES-CL'], 'launchYear': None, 'types': ['Public']}, {'date': '2019-04-23', 'localName': 'San Jorge (D\u00eda de Arag\u00f3n)', 'name': 'Day of Arag\u00f3n', 'countryCode': 'ES', 'fixed': False, 'global': False, 'counties': ['ES-AR'], 'launchYear': None, 'types': ['Public']}, {'date': '2019-05-01', 'localName': 'Fiesta del trabajo', 'name': 'Labour Day', 'countryCode': 'ES', 'fixed': False, 'global': True, 'counties': None, 'launchYear': None, 'types': ['Public']}, {'date': '2019-05-02', 'localName': 'Fiesta de la Comunidad de Madrid', 'name': 'Day of Madrid', 'countryCode': 'ES', 'fixed': False, 'global': False, 'counties': ['ES-MD'], 'launchYear': None, 'types': ['Public']}, {'date': '2019-05-17', 'localName': 'D\u00eda das Letras Galegas', 'name': 'Galician Literature Day', 'countryCode': 'ES', 'fixed': False, 'global': False, 'counties': ['ES-GA'], 'launchYear': None, 'types': ['Public']}, {'date': '2019-05-30', 'localName': 'D\u00eda de Canarias', 'name': 'Day of the Canary Islands', 'countryCode': 'ES', 'fixed': False, 'global': False, 'counties': ['ES-CN'], 'launchYear': None, 'types': ['Public']}, {'date': '2019-05-31', 'localName': 'D\u00eda de la Regi\u00f3n Castilla-La Mancha', 'name': 'Day of Castilla-La Mancha', 'countryCode': 'ES', 'fixed': False, 'global': False, 'counties': ['ES-CM'], 'launchYear': None, 'types': ['Public']}, {'date': '2019-06-09', 'localName': 'D\u00eda de La Rioja', 'name': 'Day of La Rioja', 'countryCode': 'ES', 'fixed': False, 'global': False, 'counties': ['ES-RI'], 'launchYear': None, 'types': ['Public']}, {'date': '2019-06-09', 'localName': 'D\u00eda de la Regi\u00f3n de Murcia', 'name': 'Day of Murcia', 'countryCode': 'ES', 'fixed': False, 'global': False, 'counties': ['ES-MC'], 'launchYear': None, 'types': ['Public']}, {'date': '2019-06-20', 'localName': 'Corpus Christi', 'name': 'Corpus Christi', 'countryCode': 'ES', 'fixed': False, 'global': False, 'counties': ['ES-CM'], 'launchYear': None, 'types': ['Public']}, {'date': '2019-06-24', 'localName': 'Sant Joan', 'name': \"St. John's Day\", 'countryCode': 'ES', 'fixed': False, 'global': False, 'counties': ['ES-CT', 'ES-VC'], 'launchYear': None, 'types': ['Public']}, {'date': '2019-07-25', 'localName': 'Santiago Ap\u00f3stol', 'name': 'Santiago Ap\u00f3stol', 'countryCode': 'ES', 'fixed': False, 'global': False, 'counties': ['ES-GA', 'ES-PV'], 'launchYear': None, 'types': ['Public']}, {'date': '2019-07-28', 'localName': 'D\u00eda de las Instituciones de Cantabria', 'name': 'Day of the Cantabrian Institutions', 'countryCode': 'ES', 'fixed': False, 'global': False, 'counties': ['ES-CB'], 'launchYear': None, 'types': ['Public']}, {'date': '2019-08-15', 'localName': 'Asunci\u00f3n', 'name': 'Assumption', 'countryCode': 'ES', 'fixed': False, 'global': True, 'counties': None, 'launchYear': None, 'types': ['Public']}, {'date': '2019-09-08', 'localName': 'D\u00eda de Asturias', 'name': 'Day of Asturias', 'countryCode': 'ES', 'fixed': False, 'global': False, 'counties': ['ES-AS'], 'launchYear': None, 'types': ['Public']}, {'date': '2019-09-08', 'localName': 'D\u00eda de Extremadura', 'name': 'Day of Extremadura', 'countryCode': 'ES', 'fixed': False, 'global': False, 'counties': ['ES-EX'], 'launchYear': None, 'types': ['Public']}, {'date': '2019-09-11', 'localName': 'Diada Nacional de Catalunya', 'name': 'National Day of Catalonia', 'countryCode': 'ES', 'fixed': False, 'global': False, 'counties': ['ES-CT'], 'launchYear': None, 'types': ['Public']}, {'date': '2019-09-15', 'localName': 'La Bien Aparecida', 'name': 'Regional Holiday', 'countryCode': 'ES', 'fixed': False, 'global': False, 'counties': ['ES-CB'], 'launchYear': None, 'types': ['Public']}, {'date': '2019-10-09', 'localName': 'Dia de la Comunitat Valenciana', 'name': 'Day of the Valencian Community', 'countryCode': 'ES', 'fixed': False, 'global': False, 'counties': ['ES-VC'], 'launchYear': None, 'types': ['Public']}, {'date': '2019-10-12', 'localName': 'Fiesta Nacional de Espa\u00f1a', 'name': 'Fiesta Nacional de Espa\u00f1a', 'countryCode': 'ES', 'fixed': False, 'global': True, 'counties': None, 'launchYear': None, 'types': ['Public']}, {'date': '2019-11-01', 'localName': 'D\u00eda de todos los Santos', 'name': 'All Saints Day', 'countryCode': 'ES', 'fixed': False, 'global': True, 'counties': None, 'launchYear': None, 'types': ['Public']}, {'date': '2019-12-06', 'localName': 'D\u00eda de la Constituci\u00f3n', 'name': 'Constitution Day', 'countryCode': 'ES', 'fixed': False, 'global': True, 'counties': None, 'launchYear': None, 'types': ['Public']}, {'date': '2019-12-08', 'localName': 'Inmaculada Concepci\u00f3n', 'name': 'Immaculate Conception', 'countryCode': 'ES', 'fixed': False, 'global': True, 'counties': None, 'launchYear': None, 'types': ['Public']}, {'date': '2019-12-25', 'localName': 'Navidad', 'name': 'Christmas Day', 'countryCode': 'ES', 'fixed': False, 'global': True, 'counties': None, 'launchYear': None, 'types': ['Public']}, {'date': '2019-12-26', 'localName': \"St. Stephen's Day\", 'name': 'Santiago Ap\u00f3stol', 'countryCode': 'ES', 'fixed': False, 'global': False, 'counties': ['ES-CT'], 'launchYear': None, 'types': ['Public']}]."], "sub_error_type": "executable_checker:wrong_result", "model_executed_output": [{"date": "2019-01-01", "localName": "A\u00f1o Nuevo", "name": "New Year's Day", "countryCode": "ES", "fixed": false, "global": true, "counties": null, "launchYear": null, "types": ["Public"]}, {"date": "2019-01-06", "localName": "D\u00eda de Reyes / Epifan\u00eda del Se\u00f1or", "name": "Epiphany", "countryCode": "ES", "fixed": false, "global": true, "counties": null, "launchYear": null, "types": ["Public"]}, {"date": "2019-02-28", "localName": "D\u00eda de Andaluc\u00eda", "name": "Day of Andaluc\u00eda", "countryCode": "ES", "fixed": false, "global": false, "counties": ["ES-AN"], "launchYear": null, "types": ["Public"]}, {"date": "2019-03-01", "localName": "Dia de les Illes Balears", "name": "Day of the Balearic Islands", "countryCode": "ES", "fixed": false, "global": false, "counties": ["ES-IB"], "launchYear": null, "types": ["Public"]}, {"date": "2019-03-19", "localName": "San Jos\u00e9", "name": "St. Joseph's Day", "countryCode": "ES", "fixed": false, "global": false, "counties": ["ES-GA", "ES-PV", "ES-VC"], "launchYear": null, "types": ["Public"]}, {"date": "2019-04-18", "localName": "Jueves Santo", "name": "Maundy Thursday", "countryCode": "ES", "fixed": false, "global": false, "counties": ["ES-AN", "ES-AR", "ES-CL", "ES-CM", "ES-CN", "ES-EX", "ES-GA", "ES-IB", "ES-RI", "ES-MD", "ES-MC", "ES-NC", "ES-AS", "ES-PV", "ES-CB"], "launchYear": null, "types": ["Public"]}, {"date": "2019-04-19", "localName": "Viernes Santo", "name": "Good Friday", "countryCode": "ES", "fixed": false, "global": true, "counties": null, "launchYear": null, "types": ["Public"]}, {"date": "2019-04-22", "localName": "Lunes de Pascua", "name": "Easter Monday", "countryCode": "ES", "fixed": false, "global": false, "counties": ["ES-CT", "ES-IB", "ES-RI", "ES-NC", "ES-PV", "ES-VC"], "launchYear": null, "types": ["Public"]}, {"date": "2019-04-23", "localName": "D\u00eda de Castilla y Le\u00f3n", "name": "Castile and Le\u00f3n Day", "countryCode": "ES", "fixed": false, "global": false, "counties": ["ES-CL"], "launchYear": null, "types": ["Public"]}, {"date": "2019-04-23", "localName": "San Jorge (D\u00eda de Arag\u00f3n)", "name": "Day of Arag\u00f3n", "countryCode": "ES", "fixed": false, "global": false, "counties": ["ES-AR"], "launchYear": null, "types": ["Public"]}, {"date": "2019-05-01", "localName": "Fiesta del trabajo", "name": "Labour Day", "countryCode": "ES", "fixed": false, "global": true, "counties": null, "launchYear": null, "types": ["Public"]}, {"date": "2019-05-02", "localName": "Fiesta de la Comunidad de Madrid", "name": "Day of Madrid", "countryCode": "ES", "fixed": false, "global": false, "counties": ["ES-MD"], "launchYear": null, "types": ["Public"]}, {"date": "2019-05-17", "localName": "D\u00eda das Letras Galegas", "name": "Galician Literature Day", "countryCode": "ES", "fixed": false, "global": false, "counties": ["ES-GA"], "launchYear": null, "types": ["Public"]}, {"date": "2019-05-30", "localName": "D\u00eda de Canarias", "name": "Day of the Canary Islands", "countryCode": "ES", "fixed": false, "global": false, "counties": ["ES-CN"], "launchYear": null, "types": ["Public"]}, {"date": "2019-05-31", "localName": "D\u00eda de la Regi\u00f3n Castilla-La Mancha", "name": "Day of Castilla-La Mancha", "countryCode": "ES", "fixed": false, "global": false, "counties": ["ES-CM"], "launchYear": null, "types": ["Public"]}, {"date": "2019-06-09", "localName": "D\u00eda de La Rioja", "name": "Day of La Rioja", "countryCode": "ES", "fixed": false, "global": false, "counties": ["ES-RI"], "launchYear": null, "types": ["Public"]}, {"date": "2019-06-09", "localName": "D\u00eda de la Regi\u00f3n de Murcia", "name": "Day of Murcia", "countryCode": "ES", "fixed": false, "global": false, "counties": ["ES-MC"], "launchYear": null, "types": ["Public"]}, {"date": "2019-06-20", "localName": "Corpus Christi", "name": "Corpus Christi", "countryCode": "ES", "fixed": false, "global": false, "counties": ["ES-CM"], "launchYear": null, "types": ["Public"]}, {"date": "2019-06-24", "localName": "Sant Joan", "name": "St. John's Day", "countryCode": "ES", "fixed": false, "global": false, "counties": ["ES-CT", "ES-VC"], "launchYear": null, "types": ["Public"]}, {"date": "2019-07-25", "localName": "Santiago Ap\u00f3stol", "name": "Santiago Ap\u00f3stol", "countryCode": "ES", "fixed": false, "global": false, "counties": ["ES-GA", "ES-PV"], "launchYear": null, "types": ["Public"]}, {"date": "2019-07-28", "localName": "D\u00eda de las Instituciones de Cantabria", "name": "Day of the Cantabrian Institutions", "countryCode": "ES", "fixed": false, "global": false, "counties": ["ES-CB"], "launchYear": null, "types": ["Public"]}, {"date": "2019-08-15", "localName": "Asunci\u00f3n", "name": "Assumption", "countryCode": "ES", "fixed": false, "global": true, "counties": null, "launchYear": null, "types": ["Public"]}, {"date": "2019-09-08", "localName": "D\u00eda de Asturias", "name": "Day of Asturias", "countryCode": "ES", "fixed": false, "global": false, "counties": ["ES-AS"], "launchYear": null, "types": ["Public"]}, {"date": "2019-09-08", "localName": "D\u00eda de Extremadura", "name": "Day of Extremadura", "countryCode": "ES", "fixed": false, "global": false, "counties": ["ES-EX"], "launchYear": null, "types": ["Public"]}, {"date": "2019-09-11", "localName": "Diada Nacional de Catalunya", "name": "National Day of Catalonia", "countryCode": "ES", "fixed": false, "global": false, "counties": ["ES-CT"], "launchYear": null, "types": ["Public"]}, {"date": "2019-09-15", "localName": "La Bien Aparecida", "name": "Regional Holiday", "countryCode": "ES", "fixed": false, "global": false, "counties": ["ES-CB"], "launchYear": null, "types": ["Public"]}, {"date": "2019-10-09", "localName": "Dia de la Comunitat Valenciana", "name": "Day of the Valencian Community", "countryCode": "ES", "fixed": false, "global": false, "counties": ["ES-VC"], "launchYear": null, "types": ["Public"]}, {"date": "2019-10-12", "localName": "Fiesta Nacional de Espa\u00f1a", "name": "Fiesta Nacional de Espa\u00f1a", "countryCode": "ES", "fixed": false, "global": true, "counties": null, "launchYear": null, "types": ["Public"]}, {"date": "2019-11-01", "localName": "D\u00eda de todos los Santos", "name": "All Saints Day", "countryCode": "ES", "fixed": false, "global": true, "counties": null, "launchYear": null, "types": ["Public"]}, {"date": "2019-12-06", "localName": "D\u00eda de la Constituci\u00f3n", "name": "Constitution Day", "countryCode": "ES", "fixed": false, "global": true, "counties": null, "launchYear": null, "types": ["Public"]}, {"date": "2019-12-08", "localName": "Inmaculada Concepci\u00f3n", "name": "Immaculate Conception", "countryCode": "ES", "fixed": false, "global": true, "counties": null, "launchYear": null, "types": ["Public"]}, {"date": "2019-12-25", "localName": "Navidad", "name": "Christmas Day", "countryCode": "ES", "fixed": false, "global": true, "counties": null, "launchYear": null, "types": ["Public"]}, {"date": "2019-12-26", "localName": "St. Stephen's Day", "name": "Santiago Ap\u00f3stol", "countryCode": "ES", "fixed": false, "global": false, "counties": ["ES-CT"], "launchYear": null, "types": ["Public"]}]}}, {"Model Result Index 2": {"sub_error": ["Wrong execution result for \"retrieve_holiday_by_year(year='2021',country='GB')\". Expected: [{'date': '2020-01-01', 'localName': 'Neujahr', 'name': \"New Year's Day\", 'countryCode': 'DE', 'fixed': False, 'global': True, 'counties': None, 'launchYear': None, 'types': ['Public']}, {'date': '2020-01-06', 'localName': 'Heilige Drei K\u00f6nige', 'name': 'Epiphany', 'countryCode': 'DE', 'fixed': False, 'global': False, 'counties': ['DE-BW', 'DE-BY', 'DE-ST'], 'launchYear': None, 'types': ['Public']}, {'date': '2020-03-08', 'localName': 'Internationaler Frauentag', 'name': \"International Women's Day\", 'countryCode': 'DE', 'fixed': False, 'global': False, 'counties': ['DE-BE'], 'launchYear': None, 'types': ['Public']}, {'date': '2020-04-10', 'localName': 'Karfreitag', 'name': 'Good Friday', 'countryCode': 'DE', 'fixed': False, 'global': True, 'counties': None, 'launchYear': None, 'types': ['Public']}, {'date': '2020-04-12', 'localName': 'Ostersonntag', 'name': 'Easter Sunday', 'countryCode': 'DE', 'fixed': False, 'global': False, 'counties': ['DE-BB'], 'launchYear': None, 'types': ['Public']}, {'date': '2020-04-13', 'localName': 'Ostermontag', 'name': 'Easter Monday', 'countryCode': 'DE', 'fixed': False, 'global': True, 'counties': None, 'launchYear': None, 'types': ['Public']}, {'date': '2020-05-01', 'localName': 'Tag der Arbeit', 'name': 'Labour Day', 'countryCode': 'DE', 'fixed': False, 'global': True, 'counties': None, 'launchYear': None, 'types': ['Public']}, {'date': '2020-05-08', 'localName': 'Tag der Befreiung', 'name': 'Liberation Day', 'countryCode': 'DE', 'fixed': False, 'global': False, 'counties': ['DE-BE'], 'launchYear': None, 'types': ['Public']}, {'date': '2020-05-21', 'localName': 'Christi Himmelfahrt', 'name': 'Ascension Day', 'countryCode': 'DE', 'fixed': False, 'global': True, 'counties': None, 'launchYear': None, 'types': ['Public']}, {'date': '2020-05-31', 'localName': 'Pfingstsonntag', 'name': 'Pentecost', 'countryCode': 'DE', 'fixed': False, 'global': False, 'counties': ['DE-BB', 'DE-HE'], 'launchYear': None, 'types': ['Public']}, {'date': '2020-06-01', 'localName': 'Pfingstmontag', 'name': 'Whit Monday', 'countryCode': 'DE', 'fixed': False, 'global': True, 'counties': None, 'launchYear': None, 'types': ['Public']}, {'date': '2020-06-11', 'localName': 'Fronleichnam', 'name': 'Corpus Christi', 'countryCode': 'DE', 'fixed': False, 'global': False, 'counties': ['DE-BW', 'DE-BY', 'DE-HE', 'DE-NW', 'DE-RP', 'DE-SL'], 'launchYear': None, 'types': ['Public']}, {'date': '2020-08-15', 'localName': 'Mari\u00e4 Himmelfahrt', 'name': 'Assumption Day', 'countryCode': 'DE', 'fixed': False, 'global': False, 'counties': ['DE-SL'], 'launchYear': None, 'types': ['Public']}, {'date': '2020-09-20', 'localName': 'Weltkindertag', 'name': \"World Children's Day\", 'countryCode': 'DE', 'fixed': False, 'global': False, 'counties': ['DE-TH'], 'launchYear': None, 'types': ['Public']}, {'date': '2020-10-03', 'localName': 'Tag der Deutschen Einheit', 'name': 'German Unity Day', 'countryCode': 'DE', 'fixed': False, 'global': True, 'counties': None, 'launchYear': None, 'types': ['Public']}, {'date': '2020-10-31', 'localName': 'Reformationstag', 'name': 'Reformation Day', 'countryCode': 'DE', 'fixed': False, 'global': False, 'counties': ['DE-BB', 'DE-MV', 'DE-SN', 'DE-ST', 'DE-TH', 'DE-HB', 'DE-HH', 'DE-NI', 'DE-SH'], 'launchYear': None, 'types': ['Public']}, {'date': '2020-11-01', 'localName': 'Allerheiligen', 'name': \"All Saints' Day\", 'countryCode': 'DE', 'fixed': False, 'global': False, 'counties': ['DE-BW', 'DE-BY', 'DE-NW', 'DE-RP', 'DE-SL'], 'launchYear': None, 'types': ['Public']}, {'date': '2020-11-18', 'localName': 'Bu\u00df- und Bettag', 'name': 'Repentance and Prayer Day', 'countryCode': 'DE', 'fixed': False, 'global': False, 'counties': ['DE-SN'], 'launchYear': None, 'types': ['Public']}, {'date': '2020-12-25', 'localName': 'Erster Weihnachtstag', 'name': 'Christmas Day', 'countryCode': 'DE', 'fixed': False, 'global': True, 'counties': None, 'launchYear': None, 'types': ['Public']}, {'date': '2020-12-26', 'localName': 'Zweiter Weihnachtstag', 'name': \"St. Stephen's Day\", 'countryCode': 'DE', 'fixed': False, 'global': True, 'counties': None, 'launchYear': None, 'types': ['Public']}], but got: [{'date': '2021-01-01', 'localName': \"New Year's Day\", 'name': \"New Year's Day\", 'countryCode': 'GB', 'fixed': False, 'global': False, 'counties': ['GB-NIR'], 'launchYear': None, 'types': ['Public']}, {'date': '2021-01-01', 'localName': \"New Year's Day\", 'name': \"New Year's Day\", 'countryCode': 'GB', 'fixed': False, 'global': False, 'counties': ['GB-ENG', 'GB-WLS'], 'launchYear': None, 'types': ['Public']}, {'date': '2021-01-01', 'localName': \"New Year's Day\", 'name': \"New Year's Day\", 'countryCode': 'GB', 'fixed': False, 'global': False, 'counties': ['GB-SCT'], 'launchYear': None, 'types': ['Public']}, {'date': '2021-01-02', 'localName': '2 January', 'name': '2 January', 'countryCode': 'GB', 'fixed': False, 'global': False, 'counties': ['GB-SCT'], 'launchYear': None, 'types': ['Public']}, {'date': '2021-03-17', 'localName': \"Saint Patrick's Day\", 'name': \"Saint Patrick's Day\", 'countryCode': 'GB', 'fixed': False, 'global': False, 'counties': ['GB-NIR'], 'launchYear': None, 'types': ['Public']}, {'date': '2021-04-02', 'localName': 'Good Friday', 'name': 'Good Friday', 'countryCode': 'GB', 'fixed': False, 'global': True, 'counties': None, 'launchYear': None, 'types': ['Public']}, {'date': '2021-04-05', 'localName': 'Easter Monday', 'name': 'Easter Monday', 'countryCode': 'GB', 'fixed': False, 'global': False, 'counties': ['GB-ENG', 'GB-WLS', 'GB-NIR'], 'launchYear': None, 'types': ['Public']}, {'date': '2021-05-03', 'localName': 'Early May Bank Holiday', 'name': 'Early May Bank Holiday', 'countryCode': 'GB', 'fixed': False, 'global': True, 'counties': None, 'launchYear': None, 'types': ['Public']}, {'date': '2021-05-31', 'localName': 'Spring Bank Holiday', 'name': 'Spring Bank Holiday', 'countryCode': 'GB', 'fixed': False, 'global': True, 'counties': None, 'launchYear': None, 'types': ['Public']}, {'date': '2021-07-12', 'localName': 'Battle of the Boyne', 'name': 'Battle of the Boyne', 'countryCode': 'GB', 'fixed': False, 'global': False, 'counties': ['GB-NIR'], 'launchYear': None, 'types': ['Public']}, {'date': '2021-08-02', 'localName': 'Summer Bank Holiday', 'name': 'Summer Bank Holiday', 'countryCode': 'GB', 'fixed': False, 'global': False, 'counties': ['GB-SCT'], 'launchYear': None, 'types': ['Public']}, {'date': '2021-08-30', 'localName': 'Summer Bank Holiday', 'name': 'Summer Bank Holiday', 'countryCode': 'GB', 'fixed': False, 'global': False, 'counties': ['GB-ENG', 'GB-WLS', 'GB-NIR'], 'launchYear': None, 'types': ['Public']}, {'date': '2021-11-30', 'localName': \"Saint Andrew's Day\", 'name': \"Saint Andrew's Day\", 'countryCode': 'GB', 'fixed': False, 'global': False, 'counties': ['GB-SCT'], 'launchYear': None, 'types': ['Public']}, {'date': '2021-12-27', 'localName': 'Christmas Day', 'name': 'Christmas Day', 'countryCode': 'GB', 'fixed': False, 'global': True, 'counties': None, 'launchYear': None, 'types': ['Public']}, {'date': '2021-12-28', 'localName': 'Boxing Day', 'name': \"St. Stephen's Day\", 'countryCode': 'GB', 'fixed': False, 'global': True, 'counties': None, 'launchYear': None, 'types': ['Public']}]."], "sub_error_type": "executable_checker:wrong_result", "model_executed_output": [{"date": "2021-01-01", "localName": "New Year's Day", "name": "New Year's Day", "countryCode": "GB", "fixed": false, "global": false, "counties": ["GB-NIR"], "launchYear": null, "types": ["Public"]}, {"date": "2021-01-01", "localName": "New Year's Day", "name": "New Year's Day", "countryCode": "GB", "fixed": false, "global": false, "counties": ["GB-ENG", "GB-WLS"], "launchYear": null, "types": ["Public"]}, {"date": "2021-01-01", "localName": "New Year's Day", "name": "New Year's Day", "countryCode": "GB", "fixed": false, "global": false, "counties": ["GB-SCT"], "launchYear": null, "types": ["Public"]}, {"date": "2021-01-02", "localName": "2 January", "name": "2 January", "countryCode": "GB", "fixed": false, "global": false, "counties": ["GB-SCT"], "launchYear": null, "types": ["Public"]}, {"date": "2021-03-17", "localName": "Saint Patrick's Day", "name": "Saint Patrick's Day", "countryCode": "GB", "fixed": false, "global": false, "counties": ["GB-NIR"], "launchYear": null, "types": ["Public"]}, {"date": "2021-04-02", "localName": "Good Friday", "name": "Good Friday", "countryCode": "GB", "fixed": false, "global": true, "counties": null, "launchYear": null, "types": ["Public"]}, {"date": "2021-04-05", "localName": "Easter Monday", "name": "Easter Monday", "countryCode": "GB", "fixed": false, "global": false, "counties": ["GB-ENG", "GB-WLS", "GB-NIR"], "launchYear": null, "types": ["Public"]}, {"date": "2021-05-03", "localName": "Early May Bank Holiday", "name": "Early May Bank Holiday", "countryCode": "GB", "fixed": false, "global": true, "counties": null, "launchYear": null, "types": ["Public"]}, {"date": "2021-05-31", "localName": "Spring Bank Holiday", "name": "Spring Bank Holiday", "countryCode": "GB", "fixed": false, "global": true, "counties": null, "launchYear": null, "types": ["Public"]}, {"date": "2021-07-12", "localName": "Battle of the Boyne", "name": "Battle of the Boyne", "countryCode": "GB", "fixed": false, "global": false, "counties": ["GB-NIR"], "launchYear": null, "types": ["Public"]}, {"date": "2021-08-02", "localName": "Summer Bank Holiday", "name": "Summer Bank Holiday", "countryCode": "GB", "fixed": false, "global": false, "counties": ["GB-SCT"], "launchYear": null, "types": ["Public"]}, {"date": "2021-08-30", "localName": "Summer Bank Holiday", "name": "Summer Bank Holiday", "countryCode": "GB", "fixed": false, "global": false, "counties": ["GB-ENG", "GB-WLS", "GB-NIR"], "launchYear": null, "types": ["Public"]}, {"date": "2021-11-30", "localName": "Saint Andrew's Day", "name": "Saint Andrew's Day", "countryCode": "GB", "fixed": false, "global": false, "counties": ["GB-SCT"], "launchYear": null, "types": ["Public"]}, {"date": "2021-12-27", "localName": "Christmas Day", "name": "Christmas Day", "countryCode": "GB", "fixed": false, "global": true, "counties": null, "launchYear": null, "types": ["Public"]}, {"date": "2021-12-28", "localName": "Boxing Day", "name": "St. Stephen's Day", "countryCode": "GB", "fixed": false, "global": true, "counties": null, "launchYear": null, "types": ["Public"]}]}}], "error_type": "executable_checker:cannot_find_match", "prompt": {"id": "executable_parallel_function_38", "question": "I'm planning an international conference and need to consider public holidays when scheduling. Could you retrieve the list of holidays for the United States in 2018, Germany in 2020, Spain in 2019, and the United Kingdom in 2021? It's crucial these dates are accurate to avoid any clashes with national holidays.", "function": {"name": "retrieve_holiday_by_year", "description": "Finds the holidays of a year.", "parameters": {"type": "dict", "properties": {"year": {"type": "string", "description": "The year of the holidays."}, "country": {"type": "string", "description": "The country of the holidays. Possible options: US, AT, DE, ES, FR, GB, IT, NL, PL, RO, SK, UA."}}, "required": ["year", "country"]}}, "execution_result_type": ["exact_match", "exact_match", "exact_match", "exact_match"], "ground_truth": ["retrieve_holiday_by_year(year='2018', country='US')", "retrieve_holiday_by_year(year='2020', country='DE')", "retrieve_holiday_by_year(year='2019', country='ES')", "retrieve_holiday_by_year(year='2021', country='GB')"], "execution_result": [[{"date": "2018-01-01", "localName": "New Year's Day", "name": "New Year's Day", "countryCode": "US", "fixed": false, "global": true, "counties": null, "launchYear": null, "types": ["Public"]}, {"date": "2018-01-15", "localName": "Martin Luther King, Jr. Day", "name": "Martin Luther King, Jr. Day", "countryCode": "US", "fixed": false, "global": true, "counties": null, "launchYear": null, "types": ["Public"]}, {"date": "2018-02-19", "localName": "Washington's Birthday", "name": "Presidents Day", "countryCode": "US", "fixed": false, "global": true, "counties": null, "launchYear": null, "types": ["Public"]}, {"date": "2018-03-30", "localName": "Good Friday", "name": "Good Friday", "countryCode": "US", "fixed": false, "global": false, "counties": ["US-CT", "US-DE", "US-HI", "US-IN", "US-KY", "US-LA", "US-NC", "US-ND", "US-NJ", "US-TN"], "launchYear": null, "types": ["Public"]}, {"date": "2018-03-30", "localName": "Good Friday", "name": "Good Friday", "countryCode": "US", "fixed": false, "global": false, "counties": ["US-TX"], "launchYear": null, "types": ["Optional"]}, {"date": "2018-05-28", "localName": "Memorial Day", "name": "Memorial Day", "countryCode": "US", "fixed": false, "global": true, "counties": null, "launchYear": null, "types": ["Public"]}, {"date": "2018-07-04", "localName": "Independence Day", "name": "Independence Day", "countryCode": "US", "fixed": false, "global": true, "counties": null, "launchYear": null, "types": ["Public"]}, {"date": "2018-09-03", "localName": "Labour Day", "name": "Labor Day", "countryCode": "US", "fixed": false, "global": true, "counties": null, "launchYear": null, "types": ["Public"]}, {"date": "2018-10-08", "localName": "Columbus Day", "name": "Columbus Day", "countryCode": "US", "fixed": false, "global": false, "counties": ["US-AL", "US-AZ", "US-CO", "US-CT", "US-GA", "US-ID", "US-IL", "US-IN", "US-IA", "US-KS", "US-KY", "US-LA", "US-ME", "US-MD", "US-MA", "US-MS", "US-MO", "US-MT", "US-NE", "US-NH", "US-NJ", "US-NM", "US-NY", "US-NC", "US-OH", "US-OK", "US-PA", "US-RI", "US-SC", "US-TN", "US-UT", "US-VA", "US-WV"], "launchYear": null, "types": ["Public"]}, {"date": "2018-10-08", "localName": "Indigenous Peoples' Day", "name": "Indigenous Peoples' Day", "countryCode": "US", "fixed": false, "global": false, "counties": ["US-AK", "US-HI", "US-IA", "US-MN", "US-NC", "US-SD", "US-VT"], "launchYear": null, "types": ["Public"]}, {"date": "2018-11-12", "localName": "Veterans Day", "name": "Veterans Day", "countryCode": "US", "fixed": false, "global": true, "counties": null, "launchYear": null, "types": ["Public"]}, {"date": "2018-11-22", "localName": "Thanksgiving Day", "name": "Thanksgiving Day", "countryCode": "US", "fixed": false, "global": true, "counties": null, "launchYear": null, "types": ["Public"]}, {"date": "2018-12-25", "localName": "Christmas Day", "name": "Christmas Day", "countryCode": "US", "fixed": false, "global": true, "counties": null, "launchYear": null, "types": ["Public"]}], [{"date": "2020-01-01", "localName": "Neujahr", "name": "New Year's Day", "countryCode": "DE", "fixed": false, "global": true, "counties": null, "launchYear": null, "types": ["Public"]}, {"date": "2020-01-06", "localName": "Heilige Drei K\u00f6nige", "name": "Epiphany", "countryCode": "DE", "fixed": false, "global": false, "counties": ["DE-BW", "DE-BY", "DE-ST"], "launchYear": null, "types": ["Public"]}, {"date": "2020-03-08", "localName": "Internationaler Frauentag", "name": "International Women's Day", "countryCode": "DE", "fixed": false, "global": false, "counties": ["DE-BE"], "launchYear": null, "types": ["Public"]}, {"date": "2020-04-10", "localName": "Karfreitag", "name": "Good Friday", "countryCode": "DE", "fixed": false, "global": true, "counties": null, "launchYear": null, "types": ["Public"]}, {"date": "2020-04-12", "localName": "Ostersonntag", "name": "Easter Sunday", "countryCode": "DE", "fixed": false, "global": false, "counties": ["DE-BB"], "launchYear": null, "types": ["Public"]}, {"date": "2020-04-13", "localName": "Ostermontag", "name": "Easter Monday", "countryCode": "DE", "fixed": false, "global": true, "counties": null, "launchYear": null, "types": ["Public"]}, {"date": "2020-05-01", "localName": "Tag der Arbeit", "name": "Labour Day", "countryCode": "DE", "fixed": false, "global": true, "counties": null, "launchYear": null, "types": ["Public"]}, {"date": "2020-05-08", "localName": "Tag der Befreiung", "name": "Liberation Day", "countryCode": "DE", "fixed": false, "global": false, "counties": ["DE-BE"], "launchYear": null, "types": ["Public"]}, {"date": "2020-05-21", "localName": "Christi Himmelfahrt", "name": "Ascension Day", "countryCode": "DE", "fixed": false, "global": true, "counties": null, "launchYear": null, "types": ["Public"]}, {"date": "2020-05-31", "localName": "Pfingstsonntag", "name": "Pentecost", "countryCode": "DE", "fixed": false, "global": false, "counties": ["DE-BB", "DE-HE"], "launchYear": null, "types": ["Public"]}, {"date": "2020-06-01", "localName": "Pfingstmontag", "name": "Whit Monday", "countryCode": "DE", "fixed": false, "global": true, "counties": null, "launchYear": null, "types": ["Public"]}, {"date": "2020-06-11", "localName": "Fronleichnam", "name": "Corpus Christi", "countryCode": "DE", "fixed": false, "global": false, "counties": ["DE-BW", "DE-BY", "DE-HE", "DE-NW", "DE-RP", "DE-SL"], "launchYear": null, "types": ["Public"]}, {"date": "2020-08-15", "localName": "Mari\u00e4 Himmelfahrt", "name": "Assumption Day", "countryCode": "DE", "fixed": false, "global": false, "counties": ["DE-SL"], "launchYear": null, "types": ["Public"]}, {"date": "2020-09-20", "localName": "Weltkindertag", "name": "World Children's Day", "countryCode": "DE", "fixed": false, "global": false, "counties": ["DE-TH"], "launchYear": null, "types": ["Public"]}, {"date": "2020-10-03", "localName": "Tag der Deutschen Einheit", "name": "German Unity Day", "countryCode": "DE", "fixed": false, "global": true, "counties": null, "launchYear": null, "types": ["Public"]}, {"date": "2020-10-31", "localName": "Reformationstag", "name": "Reformation Day", "countryCode": "DE", "fixed": false, "global": false, "counties": ["DE-BB", "DE-MV", "DE-SN", "DE-ST", "DE-TH", "DE-HB", "DE-HH", "DE-NI", "DE-SH"], "launchYear": null, "types": ["Public"]}, {"date": "2020-11-01", "localName": "Allerheiligen", "name": "All Saints' Day", "countryCode": "DE", "fixed": false, "global": false, "counties": ["DE-BW", "DE-BY", "DE-NW", "DE-RP", "DE-SL"], "launchYear": null, "types": ["Public"]}, {"date": "2020-11-18", "localName": "Bu\u00df- und Bettag", "name": "Repentance and Prayer Day", "countryCode": "DE", "fixed": false, "global": false, "counties": ["DE-SN"], "launchYear": null, "types": ["Public"]}, {"date": "2020-12-25", "localName": "Erster Weihnachtstag", "name": "Christmas Day", "countryCode": "DE", "fixed": false, "global": true, "counties": null, "launchYear": null, "types": ["Public"]}, {"date": "2020-12-26", "localName": "Zweiter Weihnachtstag", "name": "St. Stephen's Day", "countryCode": "DE", "fixed": false, "global": true, "counties": null, "launchYear": null, "types": ["Public"]}], [{"date": "2019-01-01", "localName": "A\u00f1o Nuevo", "name": "New Year's Day", "countryCode": "ES", "fixed": false, "global": true, "counties": null, "launchYear": null, "types": ["Public"]}, {"date": "2019-01-06", "localName": "D\u00eda de Reyes / Epifan\u00eda del Se\u00f1or", "name": "Epiphany", "countryCode": "ES", "fixed": false, "global": true, "counties": null, "launchYear": null, "types": ["Public"]}, {"date": "2019-02-28", "localName": "D\u00eda de Andaluc\u00eda", "name": "Day of Andaluc\u00eda", "countryCode": "ES", "fixed": false, "global": false, "counties": ["ES-AN"], "launchYear": null, "types": ["Public"]}, {"date": "2019-03-01", "localName": "Dia de les Illes Balears", "name": "Day of the Balearic Islands", "countryCode": "ES", "fixed": false, "global": false, "counties": ["ES-IB"], "launchYear": null, "types": ["Public"]}, {"date": "2019-03-19", "localName": "San Jos\u00e9", "name": "St. Joseph's Day", "countryCode": "ES", "fixed": false, "global": false, "counties": ["ES-GA", "ES-PV", "ES-VC"], "launchYear": null, "types": ["Public"]}, {"date": "2019-04-18", "localName": "Jueves Santo", "name": "Maundy Thursday", "countryCode": "ES", "fixed": false, "global": false, "counties": ["ES-AN", "ES-AR", "ES-CL", "ES-CM", "ES-CN", "ES-EX", "ES-GA", "ES-IB", "ES-RI", "ES-MD", "ES-MC", "ES-NC", "ES-AS", "ES-PV", "ES-CB"], "launchYear": null, "types": ["Public"]}, {"date": "2019-04-19", "localName": "Viernes Santo", "name": "Good Friday", "countryCode": "ES", "fixed": false, "global": true, "counties": null, "launchYear": null, "types": ["Public"]}, {"date": "2019-04-22", "localName": "Lunes de Pascua", "name": "Easter Monday", "countryCode": "ES", "fixed": false, "global": false, "counties": ["ES-CT", "ES-IB", "ES-RI", "ES-NC", "ES-PV", "ES-VC"], "launchYear": null, "types": ["Public"]}, {"date": "2019-04-23", "localName": "D\u00eda de Castilla y Le\u00f3n", "name": "Castile and Le\u00f3n Day", "countryCode": "ES", "fixed": false, "global": false, "counties": ["ES-CL"], "launchYear": null, "types": ["Public"]}, {"date": "2019-04-23", "localName": "San Jorge (D\u00eda de Arag\u00f3n)", "name": "Day of Arag\u00f3n", "countryCode": "ES", "fixed": false, "global": false, "counties": ["ES-AR"], "launchYear": null, "types": ["Public"]}, {"date": "2019-05-01", "localName": "Fiesta del trabajo", "name": "Labour Day", "countryCode": "ES", "fixed": false, "global": true, "counties": null, "launchYear": null, "types": ["Public"]}, {"date": "2019-05-02", "localName": "Fiesta de la Comunidad de Madrid", "name": "Day of Madrid", "countryCode": "ES", "fixed": false, "global": false, "counties": ["ES-MD"], "launchYear": null, "types": ["Public"]}, {"date": "2019-05-17", "localName": "D\u00eda das Letras Galegas", "name": "Galician Literature Day", "countryCode": "ES", "fixed": false, "global": false, "counties": ["ES-GA"], "launchYear": null, "types": ["Public"]}, {"date": "2019-05-30", "localName": "D\u00eda de Canarias", "name": "Day of the Canary Islands", "countryCode": "ES", "fixed": false, "global": false, "counties": ["ES-CN"], "launchYear": null, "types": ["Public"]}, {"date": "2019-05-31", "localName": "D\u00eda de la Regi\u00f3n Castilla-La Mancha", "name": "Day of Castilla-La Mancha", "countryCode": "ES", "fixed": false, "global": false, "counties": ["ES-CM"], "launchYear": null, "types": ["Public"]}, {"date": "2019-06-09", "localName": "D\u00eda de La Rioja", "name": "Day of La Rioja", "countryCode": "ES", "fixed": false, "global": false, "counties": ["ES-RI"], "launchYear": null, "types": ["Public"]}, {"date": "2019-06-09", "localName": "D\u00eda de la Regi\u00f3n de Murcia", "name": "Day of Murcia", "countryCode": "ES", "fixed": false, "global": false, "counties": ["ES-MC"], "launchYear": null, "types": ["Public"]}, {"date": "2019-06-20", "localName": "Corpus Christi", "name": "Corpus Christi", "countryCode": "ES", "fixed": false, "global": false, "counties": ["ES-CM"], "launchYear": null, "types": ["Public"]}, {"date": "2019-06-24", "localName": "Sant Joan", "name": "St. John's Day", "countryCode": "ES", "fixed": false, "global": false, "counties": ["ES-CT", "ES-VC"], "launchYear": null, "types": ["Public"]}, {"date": "2019-07-25", "localName": "Santiago Ap\u00f3stol", "name": "Santiago Ap\u00f3stol", "countryCode": "ES", "fixed": false, "global": false, "counties": ["ES-GA", "ES-PV"], "launchYear": null, "types": ["Public"]}, {"date": "2019-07-28", "localName": "D\u00eda de las Instituciones de Cantabria", "name": "Day of the Cantabrian Institutions", "countryCode": "ES", "fixed": false, "global": false, "counties": ["ES-CB"], "launchYear": null, "types": ["Public"]}, {"date": "2019-08-15", "localName": "Asunci\u00f3n", "name": "Assumption", "countryCode": "ES", "fixed": false, "global": true, "counties": null, "launchYear": null, "types": ["Public"]}, {"date": "2019-09-08", "localName": "D\u00eda de Asturias", "name": "Day of Asturias", "countryCode": "ES", "fixed": false, "global": false, "counties": ["ES-AS"], "launchYear": null, "types": ["Public"]}, {"date": "2019-09-08", "localName": "D\u00eda de Extremadura", "name": "Day of Extremadura", "countryCode": "ES", "fixed": false, "global": false, "counties": ["ES-EX"], "launchYear": null, "types": ["Public"]}, {"date": "2019-09-11", "localName": "Diada Nacional de Catalunya", "name": "National Day of Catalonia", "countryCode": "ES", "fixed": false, "global": false, "counties": ["ES-CT"], "launchYear": null, "types": ["Public"]}, {"date": "2019-09-15", "localName": "La Bien Aparecida", "name": "Regional Holiday", "countryCode": "ES", "fixed": false, "global": false, "counties": ["ES-CB"], "launchYear": null, "types": ["Public"]}, {"date": "2019-10-09", "localName": "Dia de la Comunitat Valenciana", "name": "Day of the Valencian Community", "countryCode": "ES", "fixed": false, "global": false, "counties": ["ES-VC"], "launchYear": null, "types": ["Public"]}, {"date": "2019-10-12", "localName": "Fiesta Nacional de Espa\u00f1a", "name": "Fiesta Nacional de Espa\u00f1a", "countryCode": "ES", "fixed": false, "global": true, "counties": null, "launchYear": null, "types": ["Public"]}, {"date": "2019-11-01", "localName": "D\u00eda de todos los Santos", "name": "All Saints Day", "countryCode": "ES", "fixed": false, "global": true, "counties": null, "launchYear": null, "types": ["Public"]}, {"date": "2019-12-06", "localName": "D\u00eda de la Constituci\u00f3n", "name": "Constitution Day", "countryCode": "ES", "fixed": false, "global": true, "counties": null, "launchYear": null, "types": ["Public"]}, {"date": "2019-12-08", "localName": "Inmaculada Concepci\u00f3n", "name": "Immaculate Conception", "countryCode": "ES", "fixed": false, "global": true, "counties": null, "launchYear": null, "types": ["Public"]}, {"date": "2019-12-25", "localName": "Navidad", "name": "Christmas Day", "countryCode": "ES", "fixed": false, "global": true, "counties": null, "launchYear": null, "types": ["Public"]}, {"date": "2019-12-26", "localName": "St. Stephen's Day", "name": "Santiago Ap\u00f3stol", "countryCode": "ES", "fixed": false, "global": false, "counties": ["ES-CT"], "launchYear": null, "types": ["Public"]}], [{"date": "2021-01-01", "localName": "New Year's Day", "name": "New Year's Day", "countryCode": "GB", "fixed": false, "global": false, "counties": ["GB-NIR"], "launchYear": null, "types": ["Public"]}, {"date": "2021-01-01", "localName": "New Year's Day", "name": "New Year's Day", "countryCode": "GB", "fixed": false, "global": false, "counties": ["GB-ENG", "GB-WLS"], "launchYear": null, "types": ["Public"]}, {"date": "2021-01-01", "localName": "New Year's Day", "name": "New Year's Day", "countryCode": "GB", "fixed": false, "global": false, "counties": ["GB-SCT"], "launchYear": null, "types": ["Public"]}, {"date": "2021-01-02", "localName": "2 January", "name": "2 January", "countryCode": "GB", "fixed": false, "global": false, "counties": ["GB-SCT"], "launchYear": null, "types": ["Public"]}, {"date": "2021-03-17", "localName": "Saint Patrick's Day", "name": "Saint Patrick's Day", "countryCode": "GB", "fixed": false, "global": false, "counties": ["GB-NIR"], "launchYear": null, "types": ["Public"]}, {"date": "2021-04-02", "localName": "Good Friday", "name": "Good Friday", "countryCode": "GB", "fixed": false, "global": true, "counties": null, "launchYear": null, "types": ["Public"]}, {"date": "2021-04-05", "localName": "Easter Monday", "name": "Easter Monday", "countryCode": "GB", "fixed": false, "global": false, "counties": ["GB-ENG", "GB-WLS", "GB-NIR"], "launchYear": null, "types": ["Public"]}, {"date": "2021-05-03", "localName": "Early May Bank Holiday", "name": "Early May Bank Holiday", "countryCode": "GB", "fixed": false, "global": true, "counties": null, "launchYear": null, "types": ["Public"]}, {"date": "2021-05-31", "localName": "Spring Bank Holiday", "name": "Spring Bank Holiday", "countryCode": "GB", "fixed": false, "global": true, "counties": null, "launchYear": null, "types": ["Public"]}, {"date": "2021-07-12", "localName": "Battle of the Boyne", "name": "Battle of the Boyne", "countryCode": "GB", "fixed": false, "global": false, "counties": ["GB-NIR"], "launchYear": null, "types": ["Public"]}, {"date": "2021-08-02", "localName": "Summer Bank Holiday", "name": "Summer Bank Holiday", "countryCode": "GB", "fixed": false, "global": false, "counties": ["GB-SCT"], "launchYear": null, "types": ["Public"]}, {"date": "2021-08-30", "localName": "Summer Bank Holiday", "name": "Summer Bank Holiday", "countryCode": "GB", "fixed": false, "global": false, "counties": ["GB-ENG", "GB-WLS", "GB-NIR"], "launchYear": null, "types": ["Public"]}, {"date": "2021-11-30", "localName": "Saint Andrew's Day", "name": "Saint Andrew's Day", "countryCode": "GB", "fixed": false, "global": false, "counties": ["GB-SCT"], "launchYear": null, "types": ["Public"]}, {"date": "2021-12-27", "localName": "Christmas Day", "name": "Christmas Day", "countryCode": "GB", "fixed": false, "global": true, "counties": null, "launchYear": null, "types": ["Public"]}, {"date": "2021-12-28", "localName": "Boxing Day", "name": "St. Stephen's Day", "countryCode": "GB", "fixed": false, "global": true, "counties": null, "launchYear": null, "types": ["Public"]}]]}, "model_result_raw": "[retrieve_holiday_by_year(year=\"2018\", country=\"DE\"), retrieve_holiday_by_year(year=\"2019\", country=\"ES\"), retrieve_holiday_by_year(year=\"2021\", country=\"GB\"), retrieve_holiday_by_year(year=\"2018\", country=\"US\")]", "model_result_decoded": ["retrieve_holiday_by_year(year='2018',country='DE')", "retrieve_holiday_by_year(year='2019',country='ES')", "retrieve_holiday_by_year(year='2021',country='GB')", "retrieve_holiday_by_year(year='2018',country='US')"]}
{"id": 44, "model_name": "claude-instant-1.2", "test_category": "executable_parallel_function", "valid": false, "error": ["Could not find a matching function among index [3] of model output for index 3 of possible answers.", {"Model Result Index 3": {"sub_error": ["Wrong execution result for 'calculate_investment_value(initial_investment=800000,annual_contribution=1500,years=10,annual_return=0.08,inflation_rate=[0.01, 0.01, 0.02, 0.02, 0.01, 0.01, 0.02, 0.02, 0.01, 0.01])'. Expected: 1521436.1672706362, but got: 1535752.1788677683."], "sub_error_type": "executable_checker:wrong_result", "model_executed_output": 1535752.1788677683}}], "error_type": "executable_checker:cannot_find_match", "prompt": {"id": "executable_parallel_function_43", "question": "I'm considering some investment scenarios and would like to understand the potential growth of my capital over different time frames and varying conditions. Could you calculate the real value of an initial investment of $1,000,000 with an annual addition of $1,000 over 3 years at a 10% annual return, considering inflation rates of 1% for the first year and 4% for the next two years? Also, for a second scenario, starting with $500,000 and adding $500 annually over 5 years with a 7% return and inflation rates of 2%, 3%, 2%, 3%, and 2%, what will the value be? For a smaller initial sum of $250,000 with a $2,000 annual contribution over 7 years at a 5% return, with inflation alternating between 1% and 2%, what is the adjusted value? Lastly, with an $800,000 initial investment, adding $1,500 yearly for 10 years at an 8% return, considering inflation oscillating between 1% and 2% every other year, what would be the final adjusted value?", "function": {"name": "calculate_investment_value", "description": "Calculates the value of an investment over time.", "parameters": {"type": "dict", "properties": {"initial_investment": {"type": "integer", "description": "The initial investment amount."}, "annual_contribution": {"type": "float", "description": "The annual contribution amount."}, "years": {"type": "integer", "description": "The number of years to calculate the investment value for."}, "annual_return": {"type": "float", "description": "The annual return rate, ranging from 0 to 1."}, "inflation_rate": {"type": "array", "items": {"type": "float"}, "description": "The inflation rate for each year in percentage, ranging from 0 to 1."}, "adjust_for_inflation": {"type": "boolean", "default": true, "description": "Whether to adjust the investment value for inflation."}}, "required": ["initial_investment", "annual_contribution", "years", "annual_return", "inflation_rate"]}}, "execution_result_type": ["exact_match", "exact_match", "exact_match", "exact_match"], "ground_truth": ["calculate_investment_value(initial_investment=1000000, annual_contribution=1000, years=3, annual_return=0.1, inflation_rate=[0.01, 0.04, 0.04])", "calculate_investment_value(initial_investment=500000, annual_contribution=500, years=5, annual_return=0.07, inflation_rate=[0.02, 0.03, 0.02, 0.03, 0.02])", "calculate_investment_value(initial_investment=250000, annual_contribution=2000, years=7, annual_return=0.05, inflation_rate=[0.01, 0.02, 0.01, 0.02, 0.01, 0.02, 0.01])", "calculate_investment_value(initial_investment=800000, annual_contribution=1500, years=10, annual_return=0.08, inflation_rate=[0.01, 0.02, 0.01, 0.02, 0.01, 0.02, 0.01, 0.02, 0.01, 0.02])"], "execution_result": [1227813.9640000002, 628718.33836, 334951.66509394953, 1521436.1672706362]}, "model_result_raw": "[calculate_investment_value(initial_investment=1000000, annual_contribution=1000, years=3, annual_return=0.1, inflation_rate=[0.01,0.04,0.04]),\n     calculate_investment_value(initial_investment=500000, annual_contribution=500, years=5, annual_return=0.07, inflation_rate=[0.02,0.03,0.02,0.03,0.02]),\n     calculate_investment_value(initial_investment=250000, annual_contribution=2000, years=7, annual_return=0.05, inflation_rate=[0.01,0.02,0.01,0.02,0.01,0.02,0.01]),\n     calculate_investment_value(initial_investment=800000, annual_contribution=1500, years=10, annual_return=0.08, inflation_rate=[0.01,0.01,0.02,0.02,0.01,0.01,0.02,0.02,0.01,0.01])]", "model_result_decoded": ["calculate_investment_value(initial_investment=1000000,annual_contribution=1000,years=3,annual_return=0.1,inflation_rate=[0.01, 0.04, 0.04])", "calculate_investment_value(initial_investment=500000,annual_contribution=500,years=5,annual_return=0.07,inflation_rate=[0.02, 0.03, 0.02, 0.03, 0.02])", "calculate_investment_value(initial_investment=250000,annual_contribution=2000,years=7,annual_return=0.05,inflation_rate=[0.01, 0.02, 0.01, 0.02, 0.01, 0.02, 0.01])", "calculate_investment_value(initial_investment=800000,annual_contribution=1500,years=10,annual_return=0.08,inflation_rate=[0.01, 0.01, 0.02, 0.02, 0.01, 0.01, 0.02, 0.02, 0.01, 0.01])"]}
{"id": 45, "model_name": "claude-instant-1.2", "test_category": "executable_parallel_function", "valid": false, "error": ["Could not find a matching function among index [2, 3] of model output for index 2 of possible answers.", {"Model Result Index 2": {"sub_error": ["Wrong execution result for \"calculate_nutritional_needs(weight=85,height=175,age=40,gender='male',activity_level=4,goal='lose')\". Expected: {'calories': 2995.7188000000006, 'proteins_g': 224.67891000000003, 'fats_g': 83.21441111111113, 'carbohydrates_g': 337.0183650000001}, but got: {'calories': 2673.7447000000006, 'proteins_g': 200.53085250000004, 'fats_g': 74.27068611111113, 'carbohydrates_g': 300.79627875000006}."], "sub_error_type": "executable_checker:wrong_result", "model_executed_output": {"calories": 2673.7447000000006, "proteins_g": 200.53085250000004, "fats_g": 74.27068611111113, "carbohydrates_g": 300.79627875000006}}}, {"Model Result Index 3": {"sub_error": ["Wrong execution result for \"calculate_nutritional_needs(weight=70,height=160,age=55,gender='female',activity_level=1,goal='lose')\". Expected: {'calories': 2995.7188000000006, 'proteins_g': 224.67891000000003, 'fats_g': 83.21441111111113, 'carbohydrates_g': 337.0183650000001}, but got: {'calories': 1122.8956, 'proteins_g': 84.21717, 'fats_g': 31.191544444444446, 'carbohydrates_g': 126.32575500000002}."], "sub_error_type": "executable_checker:wrong_result", "model_executed_output": {"calories": 1122.8956, "proteins_g": 84.21717, "fats_g": 31.191544444444446, "carbohydrates_g": 126.32575500000002}}}], "error_type": "executable_checker:cannot_find_match", "prompt": {"id": "executable_parallel_function_44", "question": "I'm working on a new fitness plan and need to tailor it specifically for a few clients with different profiles. Could you help me calculate the daily nutritional needs for a 25-year-old male (180 cm, 75 kg, moderately active, weight gain), a 30-year-old female (165 cm, 65 kg, lightly active, weight maintenance), a 40-year-old male (175 cm, 85 kg, very active, weight loss), and a 55-year-old female (160 cm, 70 kg, not very active, weight loss)?", "function": {"name": "calculate_nutritional_needs", "description": "Calculates the nutritional needs of a person based on their weight, height, age, gender, activity level, and goal.", "parameters": {"type": "dict", "properties": {"weight": {"type": "float", "description": "The weight of the person in kilograms."}, "height": {"type": "float", "description": "The height of the person in centimeters."}, "age": {"type": "float", "description": "The age of the person in years."}, "gender": {"type": "string", "description": "The gender of the person. Possible options [male, female, other]."}, "activity_level": {"type": "float", "description": "The activity level of the person. Possible options [1,2,3,4,5]."}, "goal": {"type": "string", "description": "The goal of the person. Possible options [lose, gain, maintain]."}}, "required": ["weight", "height", "age", "gender", "activity_level", "goal"]}}, "execution_result_type": ["exact_match", "exact_match", "exact_match", "exact_match"], "ground_truth": ["calculate_nutritional_needs(weight=75, height=180, age=25, gender='male', activity_level=3, goal='gain')", "calculate_nutritional_needs(weight=65, height=165, age=30, gender='female', activity_level=2, goal='maintain')", "calculate_nutritional_needs(weight=85, height=175, age=40, gender='male', activity_level=5, goal='lose')", "calculate_nutritional_needs(weight=70, height=160, age=55, gender='female', activity_level=1, goal='lose')"], "execution_result": [{"calories": 3313.2996, "proteins_g": 248.49746999999996, "fats_g": 92.03609999999999, "carbohydrates_g": 372.746205}, {"calories": 1966.1372499999995, "proteins_g": 147.46029374999995, "fats_g": 54.614923611111095, "carbohydrates_g": 221.19044062499995}, {"calories": 2995.7188000000006, "proteins_g": 224.67891000000003, "fats_g": 83.21441111111113, "carbohydrates_g": 337.0183650000001}, {"calories": 1122.8956, "proteins_g": 84.21717, "fats_g": 31.191544444444446, "carbohydrates_g": 126.32575500000002}]}, "model_result_raw": "[calculate_nutritional_needs(weight=75, height=180, age=25, gender='male', activity_level=3, goal='gain'), calculate_nutritional_needs(weight=65, height=165, age=30, gender='female', activity_level=2, goal='maintain'), calculate_nutritional_needs(weight=85, height=175, age=40, gender='male', activity_level=4, goal='lose'), calculate_nutritional_needs(weight=70, height=160, age=55, gender='female', activity_level=1, goal='lose')]", "model_result_decoded": ["calculate_nutritional_needs(weight=75,height=180,age=25,gender='male',activity_level=3,goal='gain')", "calculate_nutritional_needs(weight=65,height=165,age=30,gender='female',activity_level=2,goal='maintain')", "calculate_nutritional_needs(weight=85,height=175,age=40,gender='male',activity_level=4,goal='lose')", "calculate_nutritional_needs(weight=70,height=160,age=55,gender='female',activity_level=1,goal='lose')"]}
{"id": 46, "model_name": "claude-instant-1.2", "test_category": "executable_parallel_function", "valid": false, "error": ["Wrong number of functions provided. Expected 4, but got 1."], "error_type": "value_error:exec_result_count", "prompt": {"id": "executable_parallel_function_45", "question": "I'm planning a small get-together this weekend and I'd like to order some food for my guests. For the order, I want 10 burgers at $5 each, 7 ice creams at $2 each, 3 pizzas at $8 each, and 12 donuts at $1 each. Could you calculate the total cost for these items using your ordering system?", "function": {"name": "order_food", "description": "Orders food for a customer.Return the total price.", "parameters": {"type": "dict", "properties": {"item": {"type": "array", "items": {"type": "string", "description": "the name of the product, possible options ['fries', 'dumplings', 'pizza', 'soda', 'salad', 'rice bowl', 'burger', 'cake', 'cookie', 'ice cream', 'sandwich', 'hot dog', 'noodles', 'chicken', 'beef', 'pork', 'fish', 'shrimp', 'lobster', 'crab', 'steak']."}}, "quantity": {"type": "array", "items": {"type": "integer", "description": "the number of the product purchased."}}, "price": {"type": "array", "items": {"type": "float", "description": "the number of the product purchased."}}}, "required": ["item", "quantity", "price"]}}, "execution_result_type": ["exact_match", "exact_match", "exact_match", "exact_match"], "ground_truth": ["order_food(item=['burger'], quantity=[10], price=[5])", "order_food(item=['ice cream'], quantity=[7], price=[2])", "order_food(item=['pizza'], quantity=[3], price=[8])", "order_food(item=['donut'], quantity=[12], price=[1])"], "execution_result": [50, 14, 24, 12]}, "model_result_raw": "[order_food(item=['burger','ice cream','pizza','donut'],quantity=[10,7,3,12],price=[5,2,8,1])]", "model_result_decoded": ["order_food(item=['burger', 'ice cream', 'pizza', 'donut'],quantity=[10, 7, 3, 12],price=[5, 2, 8, 1])"]}
{"id": 47, "model_name": "claude-instant-1.2", "test_category": "executable_parallel_function", "valid": false, "error": ["Wrong number of functions provided. Expected 4, but got 1."], "error_type": "value_error:exec_result_count", "prompt": {"id": "executable_parallel_function_46", "question": "We're planning a dinner and decided to order 101 dumplings at $0.1 each, 20 rice bowls at $10 each, 50 spring rolls at $0.5 each, and 10 noodle soups at $3 each. I need to know the total cost for our meal. Can you work that out for me?", "function": {"name": "order_food", "description": "Orders food for a customer.Return the total price.", "parameters": {"type": "dict", "properties": {"item": {"type": "array", "items": {"type": "string", "description": "the name of the product, possible options ['fries', 'dumplings', 'pizza', 'soda', 'salad', 'rice bowl', 'burger', 'cake', 'cookie', 'ice cream', 'sandwich', 'hot dog', 'noodles', 'chicken', 'beef', 'pork', 'fish', 'shrimp', 'lobster', 'crab', 'steak']."}}, "quantity": {"type": "array", "items": {"type": "integer", "description": "the number of the product purchased."}}, "price": {"type": "array", "items": {"type": "float", "description": "the number of the product purchased."}}}, "required": ["item", "quantity", "price"]}}, "execution_result_type": ["exact_match", "exact_match", "exact_match", "exact_match"], "ground_truth": ["order_food(item=['dumplings'], quantity=[101], price=[0.1])", "order_food(item=['rice bowl'], quantity=[20], price=[10])", "order_food(item=['spring rolls'], quantity=[50], price=[0.5])", "order_food(item=['noodle soup'], quantity=[10], price=[3])"], "execution_result": [10.100000000000001, 200, 25.0, 30]}, "model_result_raw": "[order_food(item=['dumplings','rice bowl','spring rolls','noodle soups'],quantity=[101,20,50,10],price=[0.1,10,0.5,3])]", "model_result_decoded": ["order_food(item=['dumplings', 'rice bowl', 'spring rolls', 'noodle soups'],quantity=[101, 20, 50, 10],price=[0.1, 10, 0.5, 3])"]}
{"id": 49, "model_name": "claude-instant-1.2", "test_category": "executable_parallel_function", "valid": false, "error": ["Failed to decode executable. unterminated string literal (detected at line 1) (<unknown>, line 1)"], "error_type": "executable_decoder:decoder_failed", "prompt": {"id": "executable_parallel_function_48", "question": "I've been on a classic film binge lately and have a few iconic movies lined up for my next movie night. My cousin is staying over, so I need to ensure the films are appropriate for us to watch together. Could you check the age ratings for 'Pulp Fiction', 'The Godfather', 'Schindler's List', and 'The Dark Knight'?", "function": {"name": "get_movie_rating", "description": "Fetches the age rating of a movie from the OMDB API.", "parameters": {"type": "dict", "properties": {"movie_name": {"type": "string", "description": "The name of the movie."}}, "required": ["movie_name"]}}, "execution_result_type": ["exact_match", "exact_match", "exact_match", "exact_match"], "ground_truth": ["get_movie_rating(movie_name='Pulp Fiction')", "get_movie_rating(movie_name='The Godfather')", "get_movie_rating(movie_name=\"Schindler's List\")", "get_movie_rating(movie_name='The Dark Knight')"], "execution_result": ["R", "R", "R", "PG-13"]}, "model_result_raw": "[get_movie_rating(movie_name='Pulp Fiction'),get_movie_rating(movie_name='The Godfather'),get_movie_rating(movie_name='Schindler's List'),get_movie_rating(movie_name='The Dark Knight')]"}